Metadata-Version: 2.1
Name: jduargs
Version: 0.6.1
Summary: A simple command line argument parser package.
Home-page: https://github.com/jeandemeusy/jdu_args
Author: Jean Demeusy
Author-email: dev.jdu@gmail.com
License: UNKNOWN
Platform: UNKNOWN
Classifier: Programming Language :: Python :: 3
Classifier: License :: OSI Approved :: MIT License
Classifier: Operating System :: OS Independent
